[
  {
    "name": "Alien Mints",
    "thc": "20-25%",
    "cbd": "<1%",
    "terpengehalt": "2.68%",
    "terpenprofil": ["β-Myrcen", "β-Caryophyllen"],
    "wirkungen": ["entzündungshemmend", "neuroprotektiv"],
    "typ": "Indica-dominant",
    "status": "active"
  },
  {
    "name": "Berlin Berries",
    "thc": "25-33%",
    "cbd": "<1%",
    "terpengehalt": "3.64%",
    "terpenprofil": ["D-Limonen", "Caryophyllen"],
    "wirkungen": ["entzündungshemmend", "antioxidativ", "antimikrobiell", "stresslösend"],
    "typ": "Indica-dominant",
    "status": "active"
  },
  {
    "name": "Black Triangle",
    "thc": "18-27%",
    "cbd": "<1%",
    "terpengehalt": "2.25%",
    "terpenprofil": ["β-Caryophyllen", "Selinene"],
    "wirkungen": ["analgetisch", "entzündungshemmend"],
    "typ": "Indica-dominant",
    "status": "active"
  },
  {
    "name": "Bling Blaow",
    "thc": "25-33%",
    "cbd": "<1%",
    "terpengehalt": "3.39%",
    "terpenprofil": ["D-Limonen", "Linalool"],
    "wirkungen": ["entzündungshemmend", "antioxidativ", "antimykotisch", "stresslösend"],
    "typ": "Indica-dominant",
    "status": "active"
  },
  {
    "name": "Blue Dream",
    "thc": "16-25%",
    "cbd": "<1%",
    "terpengehalt": "1.65%",
    "terpenprofil": ["β-Caryophyllen", "Linalool"],
    "wirkungen": ["analgetisch", "entzündungshemmend"],
    "typ": "Indica-dominant",
    "status": "discontinued"
  },
  {
    "name": "Bucket List",
    "thc": "22-33%",
    "cbd": "<1%",
    "terpengehalt": "1.39%",
    "terpenprofil": ["β-Caryophyllen", "D-Limonen"],
    "wirkungen": ["analgetisch", "entzündungshemmend"],
    "typ": "Sativa",
    "status": "active" 
  },
  {
    "name": "Chemdog",
    "thc": "18-27%",
    "cbd": "<1%",
    "terpengehalt": "1.40%",
    "terpenprofil": ["β-Caryophyllen", "β-Myrcen"],
    "wirkungen": ["analgetisch", "entzündungshemmend"],
    "typ": "Indica-dominant",
    "status": "active"
  },
  {
    "name": "Cinderella Kush",
    "thc": "18-27%",
    "cbd": "<1%",
    "terpengehalt": "1.76%",
    "terpenprofil": ["D-Limonen", "β-Caryophyllen"],
    "wirkungen": ["entzündungshemmend", "antioxidativ", "antimykotisch", "stresslösend"],
    "typ": "Indica-dominant",
    "status": "active"
  },
  {
    "name": "Frosted Gumbo",
    "thc": "25-36%",
    "cbd": "<1%",
    "terpengehalt": "3.34%",
    "terpenprofil": ["β-Myrcen", "Trans-Caryophyllen"],
    "wirkungen": ["antiinflammatorisch", "neuroprotektiv"],
    "typ": "Indica-dominant",
    "status": "active"
  },
  {
    "name": "Frozen Lemon Mints",
    "thc": "20-33%",
    "cbd": "<1%",
    "terpengehalt": "2.55%",
    "terpenprofil": ["Terpinolen", "β-Caryophyllen"],
    "wirkungen": ["entzündungshemmend", "unterstützt Wundheilung"],
    "typ": "Sativa-dominant",
    "status": "active"
  },
  {
    "name": "Gastro Pop",
    "thc": "22-33%",
    "cbd": "<1%",
    "terpengehalt": "3.15%",
    "terpenprofil": ["β-Myrcen", "β-Ocimen"],
    "wirkungen": ["entzündungshemmend", "neuroprotektiv"],
    "typ": "Indica-dominant",
    "status": "active"
  },
  {
    "name": "GG4",
    "thc": "20-30%",
    "cbd": "<1%",
    "terpengehalt": "2.19%",
    "terpenprofil": ["β-Caryophyllen", "Humulen"],
    "wirkungen": ["stresslösend", "schlaffördernd", "schmerzstillend"],
    "typ": "Indica-dominant",
    "status": "active"
  },
  {
    "name": "Glaced Apricot Gelato",
    "thc": "18-33%",
    "cbd": "<1%",
    "terpengehalt": "1.93%",
    "terpenprofil": ["Trans-Caryophyllen", "Terpinolen"],
    "wirkungen": ["antiinflammatorisch", "analgetisch"],
    "typ": "Indica-dominant",
    "status": "active"
  },
  {
    "name": "GMO",
    "thc": "27-33%",
    "cbd": "<1%",
    "terpengehalt": "3.50%",
    "terpenprofil": ["Farnesen", "β-Myrcen"],
    "wirkungen": ["antioxidativ", "entzündungshemmend", "antimikrobiell"],
    "typ": "Indica-dominant",
    "status": "active"
  },
  {
    "name": "Grape Face",
    "thc": "20-27%",
    "cbd": "<1%",
    "terpengehalt": "2.25%",
    "terpenprofil": ["Caryophyllen", "Selinene"],
    "wirkungen": ["analgetisch", "entzündungshemmend"],
    "typ": "Sativa-dominant",
    "status": "active"
  },
  {
    "name": "Ice Cream Cake Kush Mints",
    "thc": "20-33%",
    "cbd": "<1%",
    "terpengehalt": "1.34%",
    "terpenprofil": ["Linalool", "Caryophyllen"],
    "wirkungen": ["analgetisch", "entspannend", "angstlösend", "krampflösend"],
    "typ": "Indica-dominant",
    "status": "active"
  },
  {
    "name": "Jealousy",
    "thc": "18-27%",
    "cbd": "<1%",
    "terpengehalt": "1.96%",
    "terpenprofil": ["D-Limonen", "Trans-Caryophyllen"],
    "wirkungen": ["entzündungshemmend", "antioxidativ", "antimykotisch", "stresslösend"],
    "typ": "Indica-dominant",
    "status": "discontinued"
  },
  {
    "name": "Lavender Cake",
    "thc": "16-25%",
    "cbd": "<1%",
    "terpengehalt": "0.98%",
    "terpenprofil": ["β-Caryophyllen", "Humulen"],
    "wirkungen": ["analgetisch", "entzündungshemmend"],
    "typ": "Indica-dominant",
    "status": "active"
  },
  {
    "name": "Legendary Larry",
    "thc": "18-27%",
    "cbd": "<1%",
    "terpengehalt": "1.88%",
    "terpenprofil": ["Trans-Caryophyllen", "β-Myrcen"],
    "wirkungen": ["entzündungshemmend", "analgetisch"],
    "typ": "Indica-dominant",
    "status": "active"
  },
  {
    "name": "Lemon Cherry Gelato",
    "thc": "18-33%",
    "cbd": "<1%",
    "terpengehalt": "1.08%",
    "terpenprofil": ["Trans-Caryophyllen", "D-Limonen"],
    "wirkungen": ["antiinflammatorisch", "analgetisch"],
    "typ": "Indica-dominant",
    "status": "active"
  },
  {
    "name": "MAC 1",
    "thc": "20-25%",
    "cbd": "<1%",
    "terpengehalt": "2.76%",
    "terpenprofil": ["Farnesen", "D-Limonen"],
    "wirkungen": ["antioxidativ", "entzündungshemmend", "antimikrobiell"],
    "typ": "Indica-dominant",
    "status": "active"
  },
  {
    "name": "Masterpiece",
    "thc": "22-33%",
    "cbd": "<1%",
    "terpengehalt": "3.43%",
    "terpenprofil": ["D-Limonen", "β-Myrcen"],
    "wirkungen": ["antiinflammatorisch", "antioxidativ", "antimykotisch", "stresslösend"],
    "typ": "Indica-dominant",
    "status": "active"
  },
  {
    "name": "Mellowz",
    "thc": "18-25%",
    "cbd": "<1%",
    "terpengehalt": "2.14%",
    "terpenprofil": ["β-Myrcen", "Caryophyllen"],
    "wirkungen": ["entzündungshemmend", "neuroprotektiv"],
    "typ": "Indica-dominant",
    "status": "active"
  },
  {
    "name": "Miracle Mints",
    "thc": "22-33%",
    "cbd": "<1%",
    "terpengehalt": "2.45%",
    "terpenprofil": ["Selinene", "Caryophyllen"],
    "wirkungen": ["analgetisch", "entzündungshemmend"],
    "typ": "Indica-dominant",
    "status": "active"
  },
  {
    "name": "Modified Grapes",
    "thc": "20-33%",
    "cbd": "<1%",
    "terpengehalt": "2.32%",
    "terpenprofil": ["Trans-Caryophyllen", "β-Myrcen"],
    "wirkungen": ["antiinflammatorisch", "analgetisch"],
    "typ": "Indica-dominant",
    "status": "active"
  },
  {
    "name": "Peach Chementine",
    "thc": "20-36%",
    "cbd": "<1%",
    "terpengehalt": "2.14%",
    "terpenprofil": ["D-Limonen", "β-Myrcen"],
    "wirkungen": ["entzündungshemmend", "antioxidativ", "antimykotisch", "stresslösend"],
    "typ": "Indica-dominant",
    "status": "active"
  },
  {
    "name": "Plum Driver",
    "thc": "20-30%",
    "cbd": "<1%",
    "terpengehalt": "1.40%",
    "terpenprofil": ["Caryophyllen", "Linalool"],
    "wirkungen": ["analgetisch", "entzündungshemmend"],
    "typ": "Indica-dominant",
    "status": "active"
  },
  {
    "name": "Private Banana",
    "thc": "18-33%",
    "cbd": "<1%",
    "terpengehalt": "1.55%",
    "terpenprofil": ["Limonen", "β-Myrcen"],
    "wirkungen": ["antiinflammatorisch", "antioxidativ", "antimykotisch", "stresslösend"],
    "typ": "Indica-dominant",
    "status": "active"
  },
  {
    "name": "Rose Gold Pavé",
    "thc": "22-33%",
    "cbd": "<1%",
    "terpengehalt": "4.15%",
    "terpenprofil": ["D-Limonen", "Linalool"],
    "wirkungen": ["entzündungshemmend", "antioxidativ", "antimykotisch", "stresslösend"],
    "typ": "Indica-dominant",
    "status": "active"
  },
  {
    "name": "Rose Gold Runtz",
    "thc": "20-30%",
    "cbd": "<1%",
    "terpengehalt": "2.98%",
    "terpenprofil": ["β-Myrcen", "Caryophyllen"],
    "wirkungen": ["entzündungshemmend", "neuroprotektiv"],
    "typ": "Indica-dominant",
    "status": "discontinued"
  },
  {
    "name": "Scoops",
    "thc": "20-27%",
    "cbd": "<1%",
    "terpengehalt": "2.57%",
    "terpenprofil": ["β-Myrcen", "β-Caryophyllen"],
    "wirkungen": ["antiinflammatorisch", "neuroprotektiv"],
    "typ": "Indica-dominant",
    "status": "active"
  },
  {
    "name": "Super Lemon G",
    "thc": "7%",
    "cbd": "7%",
    "terpengehalt": "0.98%",
    "terpenprofil": ["β-Myrcen", "Caryophyllen"],
    "wirkungen": ["entzündungshemmend", "neuroprotektiv"],
    "typ": "Sativa-dominant",
    "status": "active"
  },
  {
    "name": "Tigerz Eye",
    "thc": "20-33%",
    "cbd": "<1%",
    "terpengehalt": "1.46%",
    "terpenprofil": ["β-Myrcen", "Caryophyllen"],
    "wirkungen": ["entzündungshemmend", "neuroprotektiv"],
    "typ": "Indica-dominant",
    "status": "active"
  },
  {
    "name": "Triangle Octane",
    "thc": "25-36%",
    "cbd": "<1%",
    "terpengehalt": "3.45%",
    "terpenprofil": ["β-Myrcen", "Trans-Caryophyllen"],
    "wirkungen": ["analgetisch", "antiinflammatorisch"],
    "typ": "Indica-dominant",
    "status": "active"
  }, 
  {
    "name": "Tropicana Cookies",
    "thc": "15-22%",
    "cbd": "<1%",
    "terpengehalt": "1.29%",
    "terpenprofil": ["Caryophyllen", "Linalool"],
    "wirkungen": ["analgetisch", "entzündungshemmend"],
    "typ": "Sativa-dominant",
    "status": "active"
  },
  {
    "name": "Unicorn Cake",
    "thc": "20-33%",
    "cbd": "<1%",
    "terpengehalt": "2.55%",
    "terpenprofil": ["Farnesen", "Trans-Caryophyllen"],
    "wirkungen": ["antiinflammatorisch", "antioxidativ", "antimikrobiell"],
    "typ": "Indica-dominant",
    "status": "active"
  },
  {
    "name": "Waffle Truffle",
    "thc": "18-27%",
    "cbd": "<1%",
    "terpengehalt": "1.86%",
    "terpenprofil": ["β-Caryophyllen", "Myrcen"],
    "wirkungen": ["analgetisch", "antiinflammatorisch", "anxiolytisch", "antidepressiv"],
    "typ": "Indica-dominant",
    "status": "active"
  },
  {
    "name": "Wedding Pop Triangle",
    "thc": "20-25%",
    "cbd": "<1%",
    "terpengehalt": "1.00%",
    "terpenprofil": ["Caryophyllen", "Linalool"],
    "wirkungen": ["analgetisch", "entzündungshemmend"],
    "typ": "Sativa-dominant",
    "status": "active"
  },
  {
    "name": "Wedding Singer",
    "thc": "22-33%",
    "cbd": "<1%",
    "terpengehalt": "1.17%",
    "terpenprofil": ["Caryophyllen", "β-Myrcen"],
    "wirkungen": ["analgetisch", "entzündungshemmend"],
    "typ": "Indica-dominant",
    "status": "active"
  },
  {
    "name": "Zookies",
    "thc": "18-27%",
    "cbd": "<1%",
    "terpengehalt": "0.64%",
    "terpenprofil": ["Caryophyllen", "Linalool"],
    "wirkungen": ["analgetisch", "entzündungshemmend"],
    "typ": "Indica-dominant",
    "status": "active"
  },
  {
    "name": "Zour Apple",
    "thc": "20-30%",
    "cbd": "<1%",
    "terpengehalt": "2.37%",
    "terpenprofil": ["Terpinolen", "Caryophyllen"],
    "wirkungen": ["entzündungshemmend", "unterstützt Wundheilung"],
    "typ": "Indica-dominant",
    "status": "active"
  }
]
